{"nodes": [{"id": "src_router_guards_jsx", "label": "guards.jsx", "file_type": "code", "source_file": "src/router/guards.jsx", "source_location": "L1"}, {"id": "guards_publicroute", "label": "PublicRoute()", "file_type": "code", "source_file": "src/router/guards.jsx", "source_location": "L10"}, {"id": "guards_onboardingroute", "label": "OnboardingRoute()", "file_type": "code", "source_file": "src/router/guards.jsx", "source_location": "L22"}, {"id": "guards_protectedroute", "label": "ProtectedRoute()", "file_type": "code", "source_file": "src/router/guards.jsx", "source_location": "L35"}, {"id": "guards_adminroute", "label": "AdminRoute()", "file_type": "code", "source_file": "src/router/guards.jsx", "source_location": "L47"}], "edges": [{"source": "src_router_guards_jsx", "target": "react_router_dom", "relation": "imports_from", "confidence": "EXTRACTED", "source_file": "src/router/guards.jsx", "source_location": "L1", "weight": 1.0}, {"source": "src_router_guards_jsx", "target": "src_router_hooks_useauth", "relation": "imports_from", "confidence": "EXTRACTED", "source_file": "src/router/guards.jsx", "source_location": "L2", "weight": 1.0}, {"source": "src_router_guards_jsx", "target": "src_router_components_common_applayout", "relation": "imports_from", "confidence": "EXTRACTED", "source_file": "src/router/guards.jsx", "source_location": "L3", "weight": 1.0}, {"source": "src_router_guards_jsx", "target": "guards_publicroute", "relation": "contains", "confidence": "EXTRACTED", "source_file": "src/router/guards.jsx", "source_location": "L10", "weight": 1.0}, {"source": "src_router_guards_jsx", "target": "guards_onboardingroute", "relation": "contains", "confidence": "EXTRACTED", "source_file": "src/router/guards.jsx", "source_location": "L22", "weight": 1.0}, {"source": "src_router_guards_jsx", "target": "guards_protectedroute", "relation": "contains", "confidence": "EXTRACTED", "source_file": "src/router/guards.jsx", "source_location": "L35", "weight": 1.0}, {"source": "src_router_guards_jsx", "target": "guards_adminroute", "relation": "contains", "confidence": "EXTRACTED", "source_file": "src/router/guards.jsx", "source_location": "L47", "weight": 1.0}]}